probabledoctor/__init__.py
probabledoctor/cli.py
probabledoctor/company_learned_settings.crfsuite
probabledoctor/gender.py
probabledoctor/generic_learned_settings.crfsuite
probabledoctor/person_learned_settings.crfsuite
probabledoctor/ratios.py
probabledoctor-0.1.0.dist-info/licenses/LICENSE
probabledoctor-0.1.0.dist-info/METADATA
probabledoctor-0.1.0.dist-info/WHEEL
probabledoctor-0.1.0.dist-info/entry_points.txt
probabledoctor-0.1.0.dist-info/top_level.txt
probabledoctor-0.1.0.dist-info/RECORD
